hanzo_zap/__init__.py
hanzo_zap/client.py
hanzo_zap/server.py
hanzo_zap/types.py
hanzo_zap-0.6.0.dist-info/METADATA
hanzo_zap-0.6.0.dist-info/WHEEL
hanzo_zap-0.6.0.dist-info/RECORD
