Metadata-Version: 2.4
Name: hanzo-zap
Version: 0.6.0
Summary: Zero-copy Agent Protocol (ZAP) SDK - 1000x faster than MCP
Project-URL: Homepage, https://github.com/hanzoai/dev
Project-URL: Repository, https://github.com/hanzoai/dev/tree/main/zap
Project-URL: Documentation, https://github.com/hanzoai/dev/tree/main/zap/docs
Author-email: Hanzo AI <dev@hanzo.ai>
License-Expression: MIT
Keywords: agent,ai,hanzo,mcp,protocol,zap,zero-copy
Classifier: Development Status :: 4 - Beta
Classifier: Intended Audience :: Developers
Classifier: License :: OSI Approved :: MIT License
Classifier: Programming Language :: Python :: 3
Classifier: Programming Language :: Python :: 3.10
Classifier: Programming Language :: Python :: 3.11
Classifier: Programming Language :: Python :: 3.12
Classifier: Topic :: Software Development :: Libraries :: Python Modules
Classifier: Typing :: Typed
Requires-Python: >=3.10
